odoo/addons/purchase_start_end_dates/__init__.py
odoo/addons/purchase_start_end_dates/__manifest__.py
odoo/addons/purchase_start_end_dates/i18n/de.po
odoo/addons/purchase_start_end_dates/i18n/pt.po
odoo/addons/purchase_start_end_dates/i18n/purchase_start_end_dates.pot
odoo/addons/purchase_start_end_dates/models/__init__.py
odoo/addons/purchase_start_end_dates/models/account_invoice.py
odoo/addons/purchase_start_end_dates/models/purchase_order.py
odoo/addons/purchase_start_end_dates/static/description/icon.png
odoo/addons/purchase_start_end_dates/tests/__init__.py
odoo/addons/purchase_start_end_dates/tests/test_purchase_start_end_dates.py
odoo/addons/purchase_start_end_dates/views/purchase_order.xml
odoo12_addon_purchase_start_end_dates-12.0.1.0.0.99.dev4.dist-info/METADATA
odoo12_addon_purchase_start_end_dates-12.0.1.0.0.99.dev4.dist-info/WHEEL
odoo12_addon_purchase_start_end_dates-12.0.1.0.0.99.dev4.dist-info/top_level.txt
odoo12_addon_purchase_start_end_dates-12.0.1.0.0.99.dev4.dist-info/RECORD
